README.md
setup.cfg
setup.py
hetznercloud/__init__.py
hetznercloud/actions.py
hetznercloud/client.py
hetznercloud/constants.py
hetznercloud/datacenters.py
hetznercloud/exceptions.py
hetznercloud/floating_ips.py
hetznercloud/images.py
hetznercloud/isos.py
hetznercloud/locations.py
hetznercloud/server_types.py
hetznercloud/servers.py
hetznercloud/shared.py
hetznercloud/ssh_keys.py
hetznercloud.egg-info/PKG-INFO
hetznercloud.egg-info/SOURCES.txt
hetznercloud.egg-info/dependency_links.txt
hetznercloud.egg-info/requires.txt
hetznercloud.egg-info/top_level.txt