Metadata-Version: 1.0
Name: hetznercloud
Version: 1.0.2
Summary: Hetzner Cloud SDK
Home-page: https://github.com/elsyms/hetznercloud-py
Author: Liam Symonds
Author-email: liam@ls-software.uk
License: UNKNOWN
Keywords: hetzner,hetznercloud,hetzner cloud api,hetzner sdk,hetzner api
Platform: UNKNOWN
